adobe_analytics/__init__.py
adobe_analytics/client.py
adobe_analytics/classifications/classification_job.py
adobe_analytics/classifications/classification_uploader.py
adobe_analytics/reports/parse.py
adobe_analytics/reports/report_definition.py
adobe_analytics/reports/report_downloader.py
adobe_analytics/reports/suite.py
adobe_analytics/reports/utils.py
adobe_analytics-1.2.3.dist-info/DESCRIPTION.rst
adobe_analytics-1.2.3.dist-info/METADATA
adobe_analytics-1.2.3.dist-info/RECORD
adobe_analytics-1.2.3.dist-info/WHEEL
adobe_analytics-1.2.3.dist-info/metadata.json
adobe_analytics-1.2.3.dist-info/top_level.txt
