Metadata-Version: 2.0
Name: adobe-analytics
Version: 1.2.3
Summary: A wrapper for the Adobe Analytics API.
Home-page: https://github.com/SaturnFromTitan/adobe_analytics
Author: Martin Winkel
Author-email: martin.winkel.pps@gmail.com
License: MIT
Keywords: data analytics api wrapper adobe omniture sitecatalyst python report bi
Platform: UNKNOWN
Classifier: Intended Audience :: Developers
Classifier: License :: OSI Approved :: MIT License
Classifier: Operating System :: OS Independent
Classifier: Programming Language :: Python
Classifier: Topic :: Scientific/Engineering :: Information Analysis
Classifier: Programming Language :: Python :: 3.5
Classifier: Programming Language :: Python :: 3.6
Requires-Dist: requests
Requires-Dist: python-dateutil
Requires-Dist: more-itertools
Requires-Dist: pandas
Requires-Dist: retrying
